[
  {
    "denominacion": "Dashboard operativo",
    "prioridad": 1,
    "estado": "REVISADO",
    "usuario_prepara": "ISAAC",
    "fechaLimite": "2025-11-12",
    "consultas": 53351,
    "porcentaje": 13,
    "conErrores": false,
    "enDesarrollo": false
  },
  {
    "denominacion": "Pedidos",
    "prioridad": 2,
    "estado": "REVISADO",
    "usuario_prepara": "LUCIANO",
    "fechaLimite": "2025-11-12",
    "consultas": 40542,
    "porcentaje": 10,
    "conErrores": false,
    "enDesarrollo": false
  },
  {
    "denominacion": "Repartos office",
    "prioridad": 3,
    "estado": "REVISADO",
    "usuario_prepara": "CARPIO",
    "fechaLimite": "2025-11-12",
    "consultas": 33319,
    "porcentaje": 8,
    "conErrores": false,
    "enDesarrollo": false
  },
  {
    "denominacion": "Repartos",
    "prioridad": 4,
    "estado": "REVISADO",
    "usuario_prepara": "LUCIANO",
    "fechaLimite": "2025-11-12",
    "consultas": 28638,
    "porcentaje": 7,
    "conErrores": false,
    "enDesarrollo": false
  },
  {
    "denominacion": "Informe operativo",
    "prioridad": 5,
    "estado": "REVISADO",
    "usuario_prepara": "JOAN",
    "fechaLimite": "2025-11-12",
    "consultas": 20422,
    "porcentaje": 5,
    "conErrores": false,
    "enDesarrollo": false
  },
  {
    "denominacion": "Entrada / Salida personal",
    "prioridad": 6,
    "estado": "REVISADO",
    "usuario_prepara": "ISAAC",
    "fechaLimite": "2025-11-12",
    "consultas": 19646,
    "porcentaje": 5,
    "conErrores": false,
    "enDesarrollo": false
  },
  {
    "denominacion": "Producción",
    "prioridad": 7,
    "estado": "REVISADO",
    "usuario_prepara": "JOAN",
    "fechaLimite": "2025-11-12",
    "consultas": 18175,
    "porcentaje": 4,
    "conErrores": false,
    "enDesarrollo": false
  },
  {
    "denominacion": "Cuadrante personal",
    "prioridad": 8,
    "estado": "REVISADO",
    "usuario_prepara": "ISAAC",
    "fechaLimite": "2025-11-12",
    "consultas": 15197,
    "porcentaje": 4,
    "conErrores": false,
    "enDesarrollo": false
  },
  {
    "denominacion": "Facturación por cliente",
    "prioridad": 9,
    "estado": "REVISADO",
    "usuario_prepara": "LUCIANO",
    "fechaLimite": "2025-11-12",
    "consultas": 14971,
    "porcentaje": 4,
    "conErrores": false,
    "enDesarrollo": false
  },
  {
    "denominacion": "Personal general",
    "prioridad": 10,
    "estado": "REVISADO",
    "usuario_prepara": "LUCIANO",
    "fechaLimite": "2025-11-12",
    "consultas": 13700,
    "porcentaje": 3,
    "conErrores": false,
    "enDesarrollo": false
  },
  {
    "denominacion": "Calendario laboral",
    "prioridad": 11,
    "estado": "REVISADO",
    "usuario_prepara": "ISAAC",
    "fechaLimite": "2025-11-12",
    "consultas": 10034,
    "porcentaje": 2,
    "conErrores": false,
    "enDesarrollo": false
  },
  {
    "denominacion": "Control de kilos lavados",
    "prioridad": 12,
    "estado": "REVISADO",
    "usuario_prepara": "JOAN",
    "fechaLimite": "2025-11-12",
    "consultas": 9409,
    "porcentaje": 2,
    "conErrores": false,
    "enDesarrollo": false
  },
  {
    "denominacion": "Lectura de recursos",
    "prioridad": 13,
    "estado": "REVISADO",
    "usuario_prepara": "CARPIO",
    "fechaLimite": "2025-11-12",
    "consultas": 8642,
    "porcentaje": 2,
    "conErrores": false,
    "enDesarrollo": false
  },
  {
    "denominacion": "Validar repartos",
    "prioridad": 14,
    "estado": "REVISADO",
    "usuario_prepara": "LUCIANO",
    "fechaLimite": "2025-11-13",
    "consultas": 6326,
    "porcentaje": 1,
    "conErrores": false,
    "enDesarrollo": false
  },
  {
    "denominacion": "Consumos de lencería",
    "prioridad": 15,
    "estado": "REVISADO",
    "usuario_prepara": "CARPIO",
    "fechaLimite": "2025-11-12",
    "consultas": 6247,
    "porcentaje": 1,
    "conErrores": true,
    "enDesarrollo": true
  },
  {
    "denominacion": "Gestión de almacenes",
    "prioridad": 16,
    "estado": "IMPORTADO",
    "usuario_prepara": "CARPIO",
    "fechaLimite": "2025-11-12",
    "consultas": 5780,
    "porcentaje": 1,
    "conErrores": false,
    "enDesarrollo": false
  },
  {
    "denominacion": "Comparativa procesados - entregados",
    "prioridad": 17,
    "estado": "REVISADO",
    "usuario_prepara": "LUCIANO",
    "fechaLimite": "2025-11-14",
    "consultas": 5583,
    "porcentaje": 1,
    "conErrores": false,
    "enDesarrollo": false
  },
  {
    "denominacion": "Smart View",
    "prioridad": 18,
    "estado": "REVISADO",
    "usuario_prepara": "ISAAC",
    "fechaLimite": "2025-11-12",
    "consultas": 5319,
    "porcentaje": 1,
    "conErrores": false,
    "enDesarrollo": false
  },
  {
    "denominacion": "Presupuesto venta",
    "prioridad": 19,
    "estado": "REVISADO",
    "usuario_prepara": "JOAN",
    "fechaLimite": "2025-11-12",
    "consultas": 5267,
    "porcentaje": 1,
    "conErrores": false,
    "enDesarrollo": false
  },
  {
    "denominacion": "Estructura organizativa",
    "prioridad": 20,
    "estado": "REVISADO",
    "usuario_prepara": "CARRASCOSA",
    "fechaLimite": "2025-11-13",
    "consultas": 4833,
    "porcentaje": 1,
    "conErrores": true,
    "enDesarrollo": true
  },
  {
    "denominacion": "Factura venta",
    "prioridad": 21,
    "estado": "REVISADO",
    "usuario_prepara": "JOAN",
    "fechaLimite": "2025-11-14",
    "consultas": 4251,
    "porcentaje": 1,
    "conErrores": false,
    "enDesarrollo": false
  },
  {
    "denominacion": "Incidencias",
    "prioridad": 22,
    "estado": "REVISADO",
    "usuario_prepara": "LUCIANO",
    "fechaLimite": "2025-11-13",
    "consultas": 4138,
    "porcentaje": 1,
    "conErrores": false,
    "enDesarrollo": false
  },
  {
    "denominacion": "Calendario laboral RRHH",
    "prioridad": 23,
    "estado": "REVISADO",
    "usuario_prepara": "LUCIANO",
    "fechaLimite": "2025-11-13",
    "consultas": 3868,
    "porcentaje": 1,
    "conErrores": false,
    "enDesarrollo": false
  },
  {
    "denominacion": "Reposiciones general",
    "prioridad": 24,
    "estado": "REVISADO",
    "usuario_prepara": "LUCIANO",
    "fechaLimite": "2025-11-13",
    "consultas": 3665,
    "porcentaje": 1,
    "conErrores": false,
    "enDesarrollo": false
  },
  {
    "denominacion": "Personal (Caribe)",
    "prioridad": 25,
    "estado": "REVISADO",
    "usuario_prepara": "LUCIANO",
    "fechaLimite": "2025-11-13",
    "consultas": 3134,
    "porcentaje": 100,
    "conErrores": false,
    "enDesarrollo": false
  },
  {
    "denominacion": "Monitor SAT",
    "prioridad": 26,
    "estado": "IMPORTADO",
    "usuario_prepara": "CARPIO",
    "fechaLimite": "2025-11-13",
    "consultas": 3100,
    "porcentaje": 1,
    "conErrores": false,
    "enDesarrollo": false
  },
  {
    "denominacion": "Repartos",
    "prioridad": 27,
    "estado": "REVISADO",
    "usuario_prepara": "CARPIO",
    "fechaLimite": "2025-11-13",
    "consultas": 2877,
    "porcentaje": 99.99,
    "conErrores": true,
    "enDesarrollo": false
  },
  {
    "denominacion": "Pedido proveedor",
    "prioridad": 28,
    "estado": "IMPORTADO",
    "usuario_prepara": "JOAN",
    "fechaLimite": "2025-11-14",
    "consultas": 2538,
    "porcentaje": 1,
    "conErrores": false,
    "enDesarrollo": true
  },
  {
    "denominacion": "Reposiciones office",
    "prioridad": 29,
    "estado": "REVISADO",
    "usuario_prepara": "LUCIANO",
    "fechaLimite": "2025-11-13",
    "consultas": 2519,
    "porcentaje": 1,
    "conErrores": false,
    "enDesarrollo": false
  },
  {
    "denominacion": "Notificaciones",
    "prioridad": 30,
    "estado": "REVISADO",
    "usuario_prepara": "ISAAC",
    "fechaLimite": "2025-11-13",
    "consultas": 2514,
    "porcentaje": 1,
    "conErrores": false,
    "enDesarrollo": false
  },
  {
    "denominacion": "Control presupuestario v2",
    "prioridad": 31,
    "estado": "IMPORTADO",
    "usuario_prepara": "CARRASCOSA",
    "fechaLimite": "2025-11-13",
    "consultas": 2248,
    "porcentaje": 1,
    "conErrores": false,
    "enDesarrollo": false
  },
  {
    "denominacion": "Calendario nóminas",
    "prioridad": 32,
    "estado": "REVISADO",
    "usuario_prepara": "ISAAC",
    "fechaLimite": "2025-11-17",
    "consultas": 111,
    "porcentaje": 0,
    "conErrores": false,
    "enDesarrollo": false
  },
  {
    "denominacion": "Gestión de nóminas",
    "prioridad": 33,
    "estado": "REVISADO",
    "usuario_prepara": "ISAAC",
    "fechaLimite": "2025-11-17",
    "consultas": 2203,
    "porcentaje": 1,
    "conErrores": false,
    "enDesarrollo": false
  },
  {
    "denominacion": "Estancias",
    "prioridad": 34,
    "estado": "REVISADO",
    "usuario_prepara": "LUCIANO",
    "fechaLimite": "2025-11-13",
    "consultas": 2202,
    "porcentaje": 1,
    "conErrores": false,
    "enDesarrollo": false
  },
  {
    "denominacion": "Dashboard ejecutivo",
    "prioridad": 35,
    "estado": "PENDIENTE",
    "usuario_prepara": "ISAAC",
    "fechaLimite": "2025-11-17",
    "consultas": 4176,
    "porcentaje": 1,
    "conErrores": false,
    "enDesarrollo": true
  },
  {
    "denominacion": "Config. uniformidad",
    "prioridad": 36,
    "estado": "REVISADO",
    "usuario_prepara": "CARPIO",
    "fechaLimite": "2025-11-13",
    "consultas": 2174,
    "porcentaje": 100,
    "conErrores": false,
    "enDesarrollo": false
  },
  {
    "denominacion": "Solicitudes de alta",
    "prioridad": 37,
    "estado": "REVISADO",
    "usuario_prepara": "ISAAC",
    "fechaLimite": "2025-11-14",
    "consultas": 1933,
    "porcentaje": 0,
    "conErrores": false,
    "enDesarrollo": false
  },
  {
    "denominacion": "Informe de eventos persona",
    "prioridad": 38,
    "estado": "PENDIENTE",
    "usuario_prepara": "JOAN",
    "fechaLimite": "2025-11-14",
    "consultas": 1918,
    "porcentaje": 0,
    "conErrores": false,
    "enDesarrollo": false
  },
  {
    "denominacion": "Prev. ingresos y costes",
    "prioridad": 39,
    "estado": "REVISADO",
    "usuario_prepara": "LUCIANO",
    "fechaLimite": "2025-11-14",
    "consultas": 1793,
    "porcentaje": 0,
    "conErrores": false,
    "enDesarrollo": false
  },
  {
    "denominacion": "Solicitudes de abono",
    "prioridad": 40,
    "estado": "REVISADO",
    "usuario_prepara": "ISAAC",
    "fechaLimite": "2025-11-14",
    "consultas": 1607,
    "porcentaje": 0,
    "conErrores": false,
    "enDesarrollo": false
  },
  {
    "denominacion": "Inventarios de lencería",
    "prioridad": 41,
    "estado": "REVISADO",
    "usuario_prepara": "ISAAC",
    "fechaLimite": "2025-11-14",
    "consultas": 1706,
    "porcentaje": 0,
    "conErrores": false,
    "enDesarrollo": false
  },
  {
    "denominacion": "Asientos de nóminas",
    "prioridad": 42,
    "estado": "REVISADO",
    "usuario_prepara": "ISAAC",
    "fechaLimite": "2025-11-17",
    "consultas": 1667,
    "porcentaje": 0,
    "conErrores": false,
    "enDesarrollo": false
  },
  {
    "denominacion": "Recambios",
    "prioridad": 43,
    "estado": "PENDIENTE",
    "usuario_prepara": "CARPIO",
    "fechaLimite": "2025-11-14",
    "consultas": 1662,
    "porcentaje": 0,
    "conErrores": false,
    "enDesarrollo": false
  },
  {
    "denominacion": "Abonos",
    "prioridad": 44,
    "estado": "REVISADO",
    "usuario_prepara": "ISAAC",
    "fechaLimite": "2025-11-14",
    "consultas": 1661,
    "porcentaje": 0,
    "conErrores": false,
    "enDesarrollo": false
  },
  {
    "denominacion": "Informe de recursos humanos",
    "prioridad": 45,
    "estado": "PENDIENTE",
    "usuario_prepara": "LUCIANO",
    "fechaLimite": "2025-11-14",
    "consultas": 1622,
    "porcentaje": 0,
    "conErrores": false,
    "enDesarrollo": false
  },
  {
    "denominacion": "Rutas de expedición",
    "prioridad": 46,
    "estado": "REVISADO",
    "usuario_prepara": "ISAAC",
    "fechaLimite": "2025-11-14",
    "consultas": 1587,
    "porcentaje": 0,
    "conErrores": false,
    "enDesarrollo": false
  },
  {
    "denominacion": "Movimientos uniformidad",
    "prioridad": 47,
    "estado": "REVISADO",
    "usuario_prepara": "LUCIANO",
    "fechaLimite": "2025-11-14",
    "consultas": 1560,
    "porcentaje": 0,
    "conErrores": false,
    "enDesarrollo": false
  },
  {
    "denominacion": "Informe de inventarios",
    "prioridad": 48,
    "estado": "PENDIENTE",
    "usuario_prepara": "LUCIANO",
    "fechaLimite": "2025-11-14",
    "consultas": 1548,
    "porcentaje": 0,
    "conErrores": false,
    "enDesarrollo": false
  },
  {
    "denominacion": "Entradas Recambios",
    "prioridad": 49,
    "estado": "IMPORTADO",
    "usuario_prepara": "CARPIO",
    "fechaLimite": "2025-11-14",
    "consultas": 1499,
    "porcentaje": 0,
    "conErrores": false,
    "enDesarrollo": true
  },
  {
    "denominacion": "Movimientos Recambios",
    "prioridad": 50,
    "estado": "IMPORTADO",
    "usuario_prepara": "CARPIO",
    "fechaLimite": "2025-11-14",
    "consultas": 1492,
    "porcentaje": 0,
    "conErrores": false,
    "enDesarrollo": false
  },
  {
    "denominacion": "Gestión de finiquitos",
    "prioridad": 51,
    "estado": "REVISADO",
    "usuario_prepara": "ISAAC",
    "fechaLimite": "2025-11-14",
    "consultas": 1367,
    "porcentaje": 0,
    "conErrores": false,
    "enDesarrollo": false
  },
  {
    "denominacion": "Gestión de usuarios",
    "prioridad": 52,
    "estado": "REVISADO",
    "usuario_prepara": "CARRASCOSA",
    "fechaLimite": "2025-11-14",
    "consultas": 1355,
    "porcentaje": 0,
    "conErrores": true,
    "enDesarrollo": true
  },
  {
    "denominacion": "Maquinaria",
    "prioridad": 53,
    "estado": "REVISADO",
    "usuario_prepara": "LUCIANO",
    "fechaLimite": "2025-11-14",
    "consultas": 1136,
    "porcentaje": 0,
    "conErrores": false,
    "enDesarrollo": false
  },
  {
    "denominacion": "Traspasos Recambios",
    "prioridad": 54,
    "estado": "IMPORTADO",
    "usuario_prepara": "CARPIO",
    "fechaLimite": "2025-11-14",
    "consultas": 1131,
    "porcentaje": 0,
    "conErrores": false,
    "enDesarrollo": false
  },
  {
    "denominacion": "Facturación uniformidad",
    "prioridad": 55,
    "estado": "REVISADO",
    "usuario_prepara": "LUCIANO",
    "fechaLimite": "2025-11-14",
    "consultas": 1060,
    "porcentaje": 0,
    "conErrores": false,
    "enDesarrollo": false
  },
  {
    "denominacion": "Control de envíos",
    "prioridad": 56,
    "estado": "REVISADO",
    "usuario_prepara": "LUCIANO",
    "fechaLimite": "2025-11-14",
    "consultas": 1054,
    "porcentaje": 0,
    "conErrores": false,
    "enDesarrollo": false
  },
  {
    "denominacion": "Albarán compra",
    "prioridad": 57,
    "estado": "IMPORTADO",
    "usuario_prepara": "JOAN",
    "fechaLimite": "2025-11-14",
    "consultas": 930,
    "porcentaje": 0,
    "conErrores": false,
    "enDesarrollo": true
  },
  {
    "denominacion": "Mantenimiento preventivo",
    "prioridad": 58,
    "estado": "REVISADO",
    "usuario_prepara": "LUCIANO",
    "fechaLimite": "2025-11-14",
    "consultas": 873,
    "porcentaje": 0,
    "conErrores": false,
    "enDesarrollo": false
  },
  {
    "denominacion": "Informe cumplimiento pedidos",
    "prioridad": 59,
    "estado": "IMPORTADO",
    "usuario_prepara": "LUCIANO",
    "fechaLimite": "2025-11-17",
    "consultas": 800,
    "porcentaje": 0,
    "conErrores": false,
    "enDesarrollo": false
  },
  {
    "denominacion": "Categorías laborales",
    "prioridad": 60,
    "estado": "REVISADO",
    "usuario_prepara": "ISAAC",
    "fechaLimite": "2025-11-17",
    "consultas": 389,
    "porcentaje": 0,
    "conErrores": false,
    "enDesarrollo": false
  },
  {
    "denominacion": "Artículos",
    "prioridad": 62,
    "estado": "REVISADO",
    "usuario_prepara": "JOAN",
    "fechaLimite": "2025-11-17",
    "consultas": 599,
    "porcentaje": 0,
    "conErrores": false,
    "enDesarrollo": false
  },
  {
    "denominacion": "Órdenes de trabajo (MBC)",
    "prioridad": 63,
    "estado": "IMPORTADO",
    "usuario_prepara": "LUCIANO",
    "fechaLimite": "2025-11-17",
    "consultas": 588,
    "porcentaje": 0,
    "conErrores": false,
    "enDesarrollo": false
  },
  {
    "denominacion": "Salidas Recambios",
    "prioridad": 64,
    "estado": "IMPORTADO",
    "usuario_prepara": "CARPIO",
    "fechaLimite": "2025-11-14",
    "consultas": 588,
    "porcentaje": 0,
    "conErrores": false,
    "enDesarrollo": false
  },
  {
    "denominacion": "Cierre de datos",
    "prioridad": 65,
    "estado": "REVISADO",
    "usuario_prepara": "CARRASCOSA",
    "fechaLimite": "2025-11-17",
    "consultas": 507,
    "porcentaje": 0,
    "conErrores": true,
    "enDesarrollo": false
  },
  {
    "denominacion": "Parametrización de prendas",
    "prioridad": 66,
    "estado": "REVISADO",
    "usuario_prepara": "CARRASCOSA",
    "fechaLimite": "2025-11-17",
    "consultas": 495,
    "porcentaje": 0,
    "conErrores": true,
    "enDesarrollo": false
  },
  {
    "denominacion": "Informe de pedidos huésped",
    "prioridad": 67,
    "estado": "IMPORTADO",
    "usuario_prepara": "LUCIANO",
    "fechaLimite": "2025-11-17",
    "consultas": 476,
    "porcentaje": 0,
    "conErrores": false,
    "enDesarrollo": false
  },
  {
    "denominacion": "Clientes",
    "prioridad": 68,
    "estado": "REVISADO",
    "usuario_prepara": "JOAN",
    "fechaLimite": "2025-11-17",
    "consultas": 412,
    "porcentaje": 0,
    "conErrores": false,
    "enDesarrollo": false
  },
  {
    "denominacion": "Informe de auditorías",
    "prioridad": 69,
    "estado": "IMPORTADO",
    "usuario_prepara": "LUCIANO",
    "fechaLimite": "2025-11-17",
    "consultas": 408,
    "porcentaje": 0,
    "conErrores": false,
    "enDesarrollo": false
  },
  {
    "denominacion": "Lavandería",
    "prioridad": 70,
    "estado": "REVISADO",
    "usuario_prepara": "CARRASCOSA",
    "fechaLimite": "2025-11-17",
    "consultas": 402,
    "porcentaje": 0,
    "conErrores": false,
    "enDesarrollo": false
  },
  {
    "denominacion": "Laundry dashboard",
    "prioridad": 71,
    "estado": "REVISADO",
    "usuario_prepara": "ISAAC",
    "fechaLimite": "2025-11-17",
    "consultas": 365,
    "porcentaje": 0,
    "conErrores": false,
    "enDesarrollo": false
  },
  {
    "denominacion": "Recursos energéticos",
    "prioridad": 72,
    "estado": "REVISADO",
    "usuario_prepara": "ISAAC",
    "fechaLimite": "2025-11-17",
    "consultas": 364,
    "porcentaje": 0,
    "conErrores": false,
    "enDesarrollo": false
  },
  {
    "denominacion": "Definición de prendas",
    "prioridad": 73,
    "estado": "IMPORTADO",
    "usuario_prepara": "JOAN",
    "fechaLimite": "2025-11-17",
    "consultas": 328,
    "porcentaje": 0,
    "conErrores": false,
    "enDesarrollo": false
  },
  {
    "denominacion": "Factura compra",
    "prioridad": 74,
    "estado": "PENDIENTE",
    "usuario_prepara": "JOAN",
    "fechaLimite": "2025-11-17",
    "consultas": 320,
    "porcentaje": 0,
    "conErrores": false,
    "enDesarrollo": false
  },
  {
    "denominacion": "Informe encuestas",
    "prioridad": 75,
    "estado": "IMPORTADO",
    "usuario_prepara": "LUCIANO",
    "fechaLimite": "2025-11-17",
    "consultas": 318,
    "porcentaje": 0,
    "conErrores": false,
    "enDesarrollo": false
  },
  {
    "denominacion": "Turnos",
    "prioridad": 76,
    "estado": "REVISADO",
    "usuario_prepara": "ISAAC",
    "fechaLimite": "2025-11-18",
    "consultas": 314,
    "porcentaje": 0,
    "conErrores": false,
    "enDesarrollo": false
  },
  {
    "denominacion": "Almacenes Recambios",
    "prioridad": 77,
    "estado": "IMPORTADO",
    "usuario_prepara": "CARPIO",
    "fechaLimite": "2025-11-18",
    "consultas": 306,
    "porcentaje": 0,
    "conErrores": false,
    "enDesarrollo": false
  },
  {
    "denominacion": "Informe rechazo cliente",
    "prioridad": 78,
    "estado": "PENDIENTE",
    "usuario_prepara": "LUCIANO",
    "fechaLimite": "2025-11-14",
    "consultas": 294,
    "porcentaje": 0,
    "conErrores": false,
    "enDesarrollo": false
  },
  {
    "denominacion": "Festivos y cierres",
    "prioridad": 79,
    "estado": "REVISADO",
    "usuario_prepara": "ISAAC",
    "fechaLimite": "2025-11-18",
    "consultas": 292,
    "porcentaje": 0,
    "conErrores": false,
    "enDesarrollo": false
  },
  {
    "denominacion": "Albarán venta",
    "prioridad": 80,
    "estado": "IMPORTADO",
    "usuario_prepara": "JOAN",
    "fechaLimite": "2025-11-18",
    "consultas": 290,
    "porcentaje": 0,
    "conErrores": false,
    "enDesarrollo": false
  },
  {
    "denominacion": "Categorías de máquinas",
    "prioridad": 81,
    "estado": "IMPORTADO",
    "usuario_prepara": "LUCIANO",
    "fechaLimite": "2025-11-18",
    "consultas": 268,
    "porcentaje": 0,
    "conErrores": false,
    "enDesarrollo": false
  },
  {
    "denominacion": "Informe control almacén cliente",
    "prioridad": 82,
    "estado": "PENDIENTE",
    "usuario_prepara": "LUCIANO",
    "fechaLimite": "2025-11-14",
    "consultas": 264,
    "porcentaje": 0,
    "conErrores": false,
    "enDesarrollo": false
  },
  {
    "denominacion": "Kg. Presupuestados",
    "prioridad": 83,
    "estado": "PENDIENTE",
    "usuario_prepara": "JOAN",
    "fechaLimite": "2025-11-18",
    "consultas": 251,
    "porcentaje": 0,
    "conErrores": false,
    "enDesarrollo": false
  },
  {
    "denominacion": "Gestión de mantenimiento",
    "prioridad": 84,
    "estado": "PENDIENTE",
    "usuario_prepara": "ISAAC",
    "fechaLimite": "2025-11-18",
    "consultas": 249,
    "porcentaje": 0,
    "conErrores": false,
    "enDesarrollo": false
  },
  {
    "denominacion": "No conformidades",
    "prioridad": 85,
    "estado": "IMPORTADO",
    "usuario_prepara": "LUCIANO",
    "fechaLimite": "2025-11-18",
    "consultas": 248,
    "porcentaje": 0,
    "conErrores": false,
    "enDesarrollo": false
  },
  {
    "denominacion": "Prev. Ingresos y costes (Informe)",
    "prioridad": 86,
    "estado": "IMPORTADO",
    "usuario_prepara": "LUCIANO",
    "fechaLimite": "2025-11-18",
    "consultas": 242,
    "porcentaje": 0,
    "conErrores": false,
    "enDesarrollo": false
  },
  {
    "denominacion": "Informe clasificación sucio",
    "prioridad": 87,
    "estado": "PENDIENTE",
    "usuario_prepara": "LUCIANO",
    "fechaLimite": "2025-11-14",
    "consultas": 221,
    "porcentaje": 0,
    "conErrores": false,
    "enDesarrollo": false
  },
  {
    "denominacion": "Dashboard mantenimiento",
    "prioridad": 88,
    "estado": "PENDIENTE",
    "usuario_prepara": "ISAAC",
    "fechaLimite": "2025-11-17",
    "consultas": 214,
    "porcentaje": 0,
    "conErrores": false,
    "enDesarrollo": true
  },
  {
    "denominacion": "Auditorías",
    "prioridad": 89,
    "estado": "IMPORTADO",
    "usuario_prepara": "ISAAC",
    "fechaLimite": "2025-11-18",
    "consultas": 196,
    "porcentaje": 0,
    "conErrores": false,
    "enDesarrollo": false
  },
  {
    "denominacion": "Partes de trabajo",
    "prioridad": 90,
    "estado": "PENDIENTE",
    "usuario_prepara": "LUCIANO",
    "fechaLimite": "2025-11-18",
    "consultas": 185,
    "porcentaje": 0,
    "conErrores": false,
    "enDesarrollo": false
  },
  {
    "denominacion": "Cumplimiento de preventivo",
    "prioridad": 91,
    "estado": "PENDIENTE",
    "usuario_prepara": "LUCIANO",
    "fechaLimite": "2025-11-18",
    "consultas": 182,
    "porcentaje": 0,
    "conErrores": false,
    "enDesarrollo": false
  },
  {
    "denominacion": "Estructura operativa",
    "prioridad": 92,
    "estado": "REVISADO",
    "usuario_prepara": "LUCIANO",
    "fechaLimite": "2025-11-18",
    "consultas": 167,
    "porcentaje": 0,
    "conErrores": false,
    "enDesarrollo": false
  },
  {
    "denominacion": "Regularizaciones Recambios",
    "prioridad": 93,
    "estado": "IMPORTADO",
    "usuario_prepara": "CARPIO",
    "fechaLimite": "2025-11-19",
    "consultas": 153,
    "porcentaje": 0,
    "conErrores": false,
    "enDesarrollo": false
  },
  {
    "denominacion": "Rentabilidad por centro",
    "prioridad": 94,
    "estado": "PENDIENTE",
    "usuario_prepara": "CARRASCOSA",
    "fechaLimite": "2025-11-19",
    "consultas": 147,
    "porcentaje": 0,
    "conErrores": false,
    "enDesarrollo": false
  },
  {
    "denominacion": "Balance pedidos / repartos",
    "prioridad": 95,
    "estado": "IMPORTADO",
    "usuario_prepara": "LUCIANO",
    "fechaLimite": "2025-11-19",
    "consultas": 144,
    "porcentaje": 0,
    "conErrores": false,
    "enDesarrollo": false
  },
  {
    "denominacion": "Revisiones",
    "prioridad": 96,
    "estado": "REVISADO",
    "usuario_prepara": "CARRASCOSA",
    "fechaLimite": "2025-11-19",
    "consultas": 144,
    "porcentaje": 0,
    "conErrores": false,
    "enDesarrollo": false
  },
  {
    "denominacion": "Distribución CeCo",
    "prioridad": 97,
    "estado": "PENDIENTE",
    "usuario_prepara": "CARRASCOSA",
    "fechaLimite": "2025-11-19",
    "consultas": 142,
    "porcentaje": 0,
    "conErrores": false,
    "enDesarrollo": false
  },
  {
    "denominacion": "Proveedores",
    "prioridad": 98,
    "estado": "IMPORTADO",
    "usuario_prepara": "JOAN",
    "fechaLimite": "2025-11-19",
    "consultas": 137,
    "porcentaje": 0,
    "conErrores": false,
    "enDesarrollo": false
  },
  {
    "denominacion": "Inventarios Recambios",
    "prioridad": 99,
    "estado": "IMPORTADO",
    "usuario_prepara": "CARPIO",
    "fechaLimite": "2025-11-19",
    "consultas": 136,
    "porcentaje": 0,
    "conErrores": false,
    "enDesarrollo": false
  },
  {
    "denominacion": "Plantilla mantenimiento prev.",
    "prioridad": 100,
    "estado": "IMPORTADO",
    "usuario_prepara": "LUCIANO",
    "fechaLimite": "2025-11-19",
    "consultas": 129,
    "porcentaje": 0,
    "conErrores": false,
    "enDesarrollo": false
  },
  {
    "denominacion": "Control presupuestario",
    "prioridad": 101,
    "estado": "IMPORTADO",
    "usuario_prepara": "JOAN",
    "fechaLimite": "2025-11-19",
    "consultas": 102,
    "porcentaje": 0,
    "conErrores": false,
    "enDesarrollo": false
  },
  {
    "denominacion": "Rutas de revisión",
    "prioridad": 102,
    "estado": "IMPORTADO",
    "usuario_prepara": "ISAAC",
    "fechaLimite": "2025-11-19",
    "consultas": 101,
    "porcentaje": 0,
    "conErrores": false,
    "enDesarrollo": false
  },
  {
    "denominacion": "Reuniones comerciales",
    "prioridad": 103,
    "estado": "IMPORTADO",
    "usuario_prepara": "ISAAC",
    "fechaLimite": "2025-11-19",
    "consultas": 99,
    "porcentaje": 0,
    "conErrores": false,
    "enDesarrollo": false
  },
  {
    "denominacion": "Vehículos",
    "prioridad": 104,
    "estado": "REVISADO",
    "usuario_prepara": "CARRASCOSA",
    "fechaLimite": "2025-11-19",
    "consultas": 97,
    "porcentaje": 0,
    "conErrores": false,
    "enDesarrollo": false
  },
  {
    "denominacion": "Informes costes estructura",
    "prioridad": 105,
    "estado": "PENDIENTE",
    "usuario_prepara": "LUCIANO",
    "fechaLimite": "2025-11-19",
    "consultas": 96,
    "porcentaje": 0,
    "conErrores": false,
    "enDesarrollo": false
  },
  {
    "denominacion": "Pedido cliente",
    "prioridad": 106,
    "estado": "IMPORTADO",
    "usuario_prepara": "JOAN",
    "fechaLimite": "2025-11-20",
    "consultas": 88,
    "porcentaje": 0,
    "conErrores": false,
    "enDesarrollo": false
  },
  {
    "denominacion": "Informe cumplimiento horario",
    "prioridad": 107,
    "estado": "PENDIENTE",
    "usuario_prepara": "LUCIANO",
    "fechaLimite": "2025-11-19",
    "consultas": 84,
    "porcentaje": 0,
    "conErrores": false,
    "enDesarrollo": false
  },
  {
    "denominacion": "Control de uso",
    "prioridad": 108,
    "estado": "PENDIENTE",
    "usuario_prepara": "ISAAC",
    "fechaLimite": "2025-11-19",
    "consultas": 82,
    "porcentaje": 0,
    "conErrores": false,
    "enDesarrollo": false
  },
  {
    "denominacion": "INF Logística",
    "prioridad": 109,
    "estado": "PENDIENTE",
    "usuario_prepara": "LUCIANO",
    "fechaLimite": "2025-11-20",
    "consultas": 82,
    "porcentaje": 0,
    "conErrores": false,
    "enDesarrollo": false
  },
  {
    "denominacion": "Rutas de expedición",
    "prioridad": 110,
    "estado": "IMPORTADO",
    "usuario_prepara": "ISAAC",
    "fechaLimite": "2025-11-20",
    "consultas": 75,
    "porcentaje": 0,
    "conErrores": false,
    "enDesarrollo": false
  },
  {
    "denominacion": "Asignación CeCo",
    "prioridad": 111,
    "estado": "REVISADO",
    "usuario_prepara": "CARRASCOSA",
    "fechaLimite": "2025-11-20",
    "consultas": 61,
    "porcentaje": 0,
    "conErrores": false,
    "enDesarrollo": false
  },
  {
    "denominacion": "Abonos Recambio",
    "prioridad": 112,
    "estado": "IMPORTADO",
    "usuario_prepara": "CARPIO",
    "fechaLimite": "2025-11-20",
    "consultas": 58,
    "porcentaje": 0,
    "conErrores": false,
    "enDesarrollo": false
  },
  {
    "denominacion": "Proveedores (Recambios)",
    "prioridad": 113,
    "estado": "IMPORTADO",
    "usuario_prepara": "CARPIO",
    "fechaLimite": "2025-11-20",
    "consultas": 58,
    "porcentaje": 0,
    "conErrores": false,
    "enDesarrollo": false
  },
  {
    "denominacion": "Distribución Kg",
    "prioridad": 114,
    "estado": "PENDIENTE",
    "usuario_prepara": "JOAN",
    "fechaLimite": "2025-11-20",
    "consultas": 50,
    "porcentaje": 0,
    "conErrores": false,
    "enDesarrollo": false
  },
  {
    "denominacion": "Producción de lavadoras",
    "prioridad": 115,
    "estado": "IMPORTADO",
    "usuario_prepara": "JOAN",
    "fechaLimite": "2025-11-20",
    "consultas": 48,
    "porcentaje": 0,
    "conErrores": false,
    "enDesarrollo": false
  },
  {
    "denominacion": "Agrupación PEP",
    "prioridad": 116,
    "estado": "REVISADO",
    "usuario_prepara": "CARRASCOSA",
    "fechaLimite": "2025-11-20",
    "consultas": 46,
    "porcentaje": 0,
    "conErrores": false,
    "enDesarrollo": false
  },
  {
    "denominacion": "Dashboard financiero",
    "prioridad": 117,
    "estado": "IMPORTADO",
    "usuario_prepara": "LUCIANO",
    "fechaLimite": "2025-11-20",
    "consultas": 40,
    "porcentaje": 0,
    "conErrores": false,
    "enDesarrollo": false
  },
  {
    "denominacion": "Kg. Lavados",
    "prioridad": 118,
    "estado": "IMPORTADO",
    "usuario_prepara": "LUCIANO",
    "fechaLimite": "2025-11-20",
    "consultas": 31,
    "porcentaje": 0,
    "conErrores": false,
    "enDesarrollo": false
  },
  {
    "denominacion": "Validación factura",
    "prioridad": 119,
    "estado": "PENDIENTE",
    "usuario_prepara": "CARPIO",
    "fechaLimite": "2025-11-20",
    "consultas": 30,
    "porcentaje": 0,
    "conErrores": false,
    "enDesarrollo": false
  },
  {
    "denominacion": "Datos financieros",
    "prioridad": 120,
    "estado": "IMPORTADO",
    "usuario_prepara": "CARRASCOSA",
    "fechaLimite": "2025-11-20",
    "consultas": 23,
    "porcentaje": 0,
    "conErrores": false,
    "enDesarrollo": false
  },
  {
    "denominacion": "Validación nómina",
    "prioridad": 121,
    "estado": "PENDIENTE",
    "usuario_prepara": "ISAAC",
    "fechaLimite": "2025-11-20",
    "consultas": 18,
    "porcentaje": 0,
    "conErrores": false,
    "enDesarrollo": false
  },
  {
    "denominacion": "Informe control de horas TI",
    "prioridad": 122,
    "estado": "PENDIENTE",
    "usuario_prepara": "DAVID",
    "fechaLimite": "2025-11-20",
    "consultas": 17,
    "porcentaje": 0,
    "conErrores": false,
    "enDesarrollo": false
  },
  {
    "denominacion": "Config. Auditorias",
    "prioridad": 123,
    "estado": "IMPORTADO",
    "usuario_prepara": "ISAAC",
    "fechaLimite": "2025-11-20",
    "consultas": 11,
    "porcentaje": 0,
    "conErrores": false,
    "enDesarrollo": false
  },
  {
    "denominacion": "Distribución de recursos TI",
    "prioridad": 124,
    "estado": "PENDIENTE",
    "usuario_prepara": "DAVID",
    "fechaLimite": "2025-11-20",
    "consultas": 6,
    "porcentaje": 0,
    "conErrores": false,
    "enDesarrollo": false
  },
  {
    "denominacion": "Informe repartos huésped",
    "prioridad": 125,
    "estado": "IMPORTADO",
    "usuario_prepara": "LUCIANO",
    "fechaLimite": "2025-11-20",
    "consultas": 2,
    "porcentaje": 0,
    "conErrores": false,
    "enDesarrollo": false
  }
]